rapidchecker/__init__.py
rapidchecker/__main__.py
rapidchecker/check.py
rapidchecker/cli.py
rapidchecker/config.py
rapidchecker/io.py
rapidchecker/whitespace_checks.py
rapidchecker/parser/__init__.py
rapidchecker/parser/grammar.py
rapidchecker/parser/identifiers.py
rapidchecker/parser/indent.py
rapidchecker/parser/literals.py
rapidchecker/parser/operators.py
rapidchecker/parser/tokens.py
rapidchecker-0.1.5.dist-info/licenses/LICENSE
rapidchecker-0.1.5.dist-info/METADATA
rapidchecker-0.1.5.dist-info/WHEEL
rapidchecker-0.1.5.dist-info/top_level.txt
rapidchecker-0.1.5.dist-info/RECORD
