Metadata-Version: 2.4
Name: rapidchecker
Version: 0.1.5
Summary:  Grammar and format checker for ABB RAPID code. 
Project-URL: Homepage, https://github.com/OdysseasKr/rapidchecker
Project-URL: Issues, https://github.com/OdysseasKr/rapidchecker/issues
Requires-Python: >=3.10
License-File: LICENSE
Requires-Dist: click>=7.0.0
Requires-Dist: pyparsing>=3.2.0
Requires-Dist: rich>=13.9.2
Dynamic: license-file
